VectorAnalysis/VectorAnalysis.py
VectorAnalysis/__init__.py
VectorAnalysis-0.0.3.dist-info/LICENSE.txt
VectorAnalysis-0.0.3.dist-info/LICENSE.txt:Zone.Identifier
VectorAnalysis-0.0.3.dist-info/METADATA
VectorAnalysis-0.0.3.dist-info/WHEEL
VectorAnalysis-0.0.3.dist-info/top_level.txt
VectorAnalysis-0.0.3.dist-info/RECORD
