Metadata-Version: 2.1
Name: VectorAnalysis
Version: 0.0.3
Summary: how to culculate gradient, divergence and curl
Author: tokuda
Author-email: tokuda@sciencepark.co.jp
Classifier: Programming Language :: Python :: 3
Classifier: License :: OSI Approved :: MIT License
Classifier: Operating System :: OS Independent
Requires-Python: >=3.8
License-File: LICENSE.txt
License-File: LICENSE.txt:Zone.Identifier
